wparc/__init__.py
wparc/__main__.py
wparc/core.py
wparc/exceptions.py
wparc/utils.py
wparc/cmds/__init__.py
wparc/cmds/extractor.py
wparc/data/__init__.py
wparc/data/known_routes.yml
wparc/wpapi/__init__.py
wparc/wpapi/crawler.py
wparc-1.0.7.dist-info/licenses/LICENSE
wparc-1.0.7.dist-info/METADATA
wparc-1.0.7.dist-info/WHEEL
wparc-1.0.7.dist-info/entry_points.txt
wparc-1.0.7.dist-info/top_level.txt
wparc-1.0.7.dist-info/RECORD
