Metadata-Version: 2.4
Name: wparc
Version: 1.0.7
Summary: WordPress API Crawler and Backup Tool
Home-page: https://github.com/ruarxive/wparc/
Download-URL: https://github.com/ruarxive/wparc/
Author: Ivan Begtin
Author-email: Ivan Begtin <ivan@begtin.tech>
License-Expression: MIT
Project-URL: Homepage, https://github.com/ruarxive/wparc
Project-URL: Documentation, https://github.com/ruarxive/wparc#readme
Project-URL: Repository, https://github.com/ruarxive/wparc
Project-URL: Issues, https://github.com/ruarxive/wparc/issues
Keywords: backup,archive,wordpress,rest-api,crawler
Classifier: Development Status :: 5 - Production/Stable
Classifier: Programming Language :: Python
Classifier: Programming Language :: Python :: 3 :: Only
Classifier: Programming Language :: Python :: 3.6
Classifier: Programming Language :: Python :: 3.7
Classifier: Programming Language :: Python :: 3.8
Classifier: Programming Language :: Python :: 3.9
Classifier: Programming Language :: Python :: 3.10
Classifier: Programming Language :: Python :: 3.11
Classifier: Programming Language :: Python :: 3.12
Classifier: Environment :: Console
Classifier: Intended Audience :: Developers
Classifier: Intended Audience :: System Administrators
Classifier: Topic :: Software Development
Classifier: Topic :: System :: Networking
Classifier: Topic :: Terminals
Classifier: Topic :: Text Processing
Classifier: Topic :: Utilities
Requires-Python: >=3.6
License-File: LICENSE
Requires-Dist: lxml
Requires-Dist: typer
Requires-Dist: pyyaml
Requires-Dist: requests
Requires-Dist: urllib3
Provides-Extra: dev
Requires-Dist: pytest; extra == "dev"
Requires-Dist: tox; extra == "dev"
Requires-Dist: docutils; extra == "dev"
Requires-Dist: wheel; extra == "dev"
Requires-Dist: twine; extra == "dev"
Requires-Dist: pygments>=2.7.4; extra == "dev"
Dynamic: author
Dynamic: download-url
Dynamic: home-page
Dynamic: license-file
